powerbin/CHANGELOG.rst
powerbin/LICENSE.txt
powerbin/README.rst
powerbin/__init__.py
powerbin/bin_accretion.py
powerbin/early_stopper.py
powerbin/plotting.py
powerbin/powerbin.py
powerbin/examples/__init__.py
powerbin/examples/powerbin_example.py
powerbin/examples/sample_data_ngc2273.txt
powerbin-1.1.11.dist-info/METADATA
powerbin-1.1.11.dist-info/WHEEL
powerbin-1.1.11.dist-info/top_level.txt
powerbin-1.1.11.dist-info/zip-safe
powerbin-1.1.11.dist-info/RECORD
