Metadata-Version: 2.4
Name: powerbin
Version: 1.1.11
Summary: PowerBin: Fast Adaptive Data Binning with Centroidal Power Diagrams
Home-page: https://pypi.org/project/powerbin/
Author: Michele Cappellari
Author-email: michele.cappellari@physics.ox.ac.uk
License: Other/Proprietary License
Classifier: Development Status :: 5 - Production/Stable
Classifier: Intended Audience :: Developers
Classifier: Intended Audience :: Science/Research
Classifier: Operating System :: OS Independent
Classifier: Programming Language :: Python :: 3
Requires-Dist: plotbin
Requires-Dist: numpy
Requires-Dist: scipy
Requires-Dist: matplotlib
Dynamic: author
Dynamic: author-email
Dynamic: classifier
Dynamic: description
Dynamic: description-content-type
Dynamic: home-page
Dynamic: license
Dynamic: requires-dist
Dynamic: summary
